{
    "comments": [
        {
            "author": null,
            "body": "fixed for 5.5.11",
            "date": "20050727T02:55:20",
            "id": 0
        }
    ],
    "component": "Catalina",
    "description": "setclasspath.sh has no \"#!/bin/sh\" header line, so it has no excutive \nattribute under cygwin, so in setclasspath.sh itself:\n[ ! -x \"$BASEDIR\"/bin/setclasspath.sh ]\nwill always be true. So the script exit immediately.",
    "hasPatch": false,
    "hasScreenshot": false,
    "id": "35865",
    "issuetypeClassified": "BUG",
    "issuetypeTracker": "BUG",
    "priority": "P2 normal",
    "product": "Tomcat 5",
    "project": "TOMCAT",
    "summary": "setclasspath.sh cannt be excutive under cygwin",
    "systemSpecification": true,
    "version": "5.5.9"
}