{
    "comments": [
        {
            "author": null,
            "body": "fixed in svn ",
            "date": "20060207T14:25:16",
            "id": 0
        }
    ],
    "component": "Unknown",
    "description": "The 'Logging' page of Tomcat FAQ page ([1]) contains a link to the printer-\nfriendly version of the page. The link is broken: it references a wrong page \n([2]).\n\nThe correct address for the link would be [3].\n\n\n[1] http://tomcat.apache.org/faq/logging.html\n\n[2] http://tomcat.apache.org/faq/printer/security.html\n[3] http://tomcat.apache.org/faq/printer/logging.html",
    "hasPatch": false,
    "hasScreenshot": false,
    "id": "38551",
    "issuetypeClassified": "OTHER",
    "issuetypeTracker": "BUG",
    "priority": "P2 trivial",
    "product": "Tomcat 5",
    "project": "TOMCAT",
    "summary": "Broked link to printer-frendly version on a FAQ page",
    "systemSpecification": true,
    "version": "Unknown"
}