{
    "comments": [
        {
            "author": null,
            "body": "Created attachment 17903\nPatch against tomcat-native-1.1.2",
            "date": "20060315T18:10:23",
            "id": 0
        },
        {
            "author": null,
            "body": "Seems like a good patch and simple to apply.",
            "date": "20061224T18:47:19",
            "id": 1
        },
        {
            "author": null,
            "body": "Looks like someone beat me to it ;)",
            "date": "20061224T18:48:51",
            "id": 2
        }
    ],
    "component": "Unknown",
    "description": "With APR enabled, the OS memory stats shown by the status servlet are incorrect\nfor Linux machines with >4G memory (real + swap).  The mem_unit value returned\nby the sysinfo system call is ignored.  For <4G machines, mem_unit is set to 1\nand the bug is not apparent.",
    "hasPatch": true,
    "hasScreenshot": false,
    "id": "38985",
    "issuetypeClassified": "BUG",
    "issuetypeTracker": "BUG",
    "priority": "P2 normal",
    "product": "Tomcat 5",
    "project": "TOMCAT",
    "summary": "Status servlet OS memory stats incorrect",
    "systemSpecification": true,
    "version": "5.5.15"
}