{
    "comments": [
        {
            "author": "dion gillard",
            "body": "Recent commits to Cookie.java have resolved this by changing the compare method\nto check for nulls and only using the path for ordering as per the rfc",
            "date": "2002-02-19T08:17:38.000+0000",
            "id": 0
        }
    ],
    "component": "HttpClient (classic)",
    "description": "The compare method cannot handle the path being null",
    "hasPatch": false,
    "hasScreenshot": false,
    "id": "HTTPCLIENT-9",
    "issuetypeClassified": "BUG",
    "issuetypeTracker": "BUG",
    "priority": "Major",
    "product": "HTTPCLIENT",
    "project": "HTTPCLIENT",
    "summary": "Null paths break the compare method",
    "systemSpecification": true,
    "version": ""
}