{
    "comments": [
        {
            "author": "Mark Miller",
            "body": "this one snuck by my",
            "date": "2009-08-28T13:06:22.217+0000",
            "id": 0
        },
        {
            "author": "Mark Miller",
            "body": "grr - embarrsing - spent all that time with the src dist and not enough with the binary dist - db and misc are missing too - I\"ve fixed db and analyzers working on misc now",
            "date": "2009-08-28T13:22:10.891+0000",
            "id": 1
        },
        {
            "author": "Uwe Schindler",
            "body": "is this because analyzers and db have sub-module folders?",
            "date": "2009-08-28T13:25:51.653+0000",
            "id": 2
        },
        {
            "author": "Mark Miller",
            "body": "okay - misc is there - there is also just a miscellaneous folder with just a readme.txt in it - about to find the fix for that...",
            "date": "2009-08-28T13:27:47.250+0000",
            "id": 3
        },
        {
            "author": "Mark Miller",
            "body": "bq. is this because analyzers and db have sub-module folders? \n\nYup - the build process only went 1 deep for jars",
            "date": "2009-08-28T13:28:13.052+0000",
            "id": 4
        },
        {
            "author": "Mark Miller",
            "body": "the misc problem stems from having the folder as miscellanous and then a shorted misc form that gets sent out - this is confusing an error prone - other build files have to refer to both long and short version. I'm just going to rename the folder to misc and make everything the short version unless anyone objects.",
            "date": "2009-08-28T13:46:13.070+0000",
            "id": 5
        },
        {
            "author": "Mark Miller",
            "body": "okay - I think I've addressed it all - will leave this open until im 1000% sure",
            "date": "2009-08-28T14:17:02.096+0000",
            "id": 6
        },
        {
            "author": "Mark Miller",
            "body": "Okay, I think its good - that misc issue was actually in the last release so I think I made the right move with the rename",
            "date": "2009-08-28T15:36:42.325+0000",
            "id": 7
        }
    ],
    "component": "general/build",
    "description": "dists include analyzer contrib in src dist but not binary dist",
    "hasPatch": false,
    "hasScreenshot": false,
    "id": "LUCENE-1870",
    "issuetypeClassified": "OTHER",
    "issuetypeTracker": "BUG",
    "priority": "Blocker",
    "product": "LUCENE",
    "project": "LUCENE",
    "summary": "dists include analyzer contrib in src dist but not binary dist",
    "systemSpecification": true,
    "version": ""
}