{
    "comments": [
        {
            "author": "Michael McCandless",
            "body": "+1\n",
            "date": "2011-09-27T12:40:56.774+0000",
            "id": 0
        },
        {
            "author": "Martijn van Groningen",
            "body": "Committed r1177008",
            "date": "2011-09-28T18:41:20.413+0000",
            "id": 1
        }
    ],
    "component": "modules/grouping",
    "description": "Currently FirstPassGroupingCollector uses last and remove method (TreeSet) for replacing a more relevant grouping during grouping.\nThis can be replaced by pollLast since Lucene trunk is now Java 6. TermFirstPassGroupingCollectorJava6 in Solr can be removed as well.",
    "hasPatch": true,
    "hasScreenshot": false,
    "id": "LUCENE-3468",
    "issuetypeClassified": "IMPROVEMENT",
    "issuetypeTracker": "IMPROVEMENT",
    "priority": "Major",
    "product": "LUCENE",
    "project": "LUCENE",
    "summary": "FirstPassGroupingCollector should use pollLast()",
    "systemSpecification": true,
    "version": "4.0-ALPHA"
}