{
    "comments": [
        {
            "author": "David Mark Nemeskey",
            "body": "docLen changed from int to float.",
            "date": "2011-08-20T13:17:20.792+0000",
            "id": 0
        },
        {
            "author": "Robert Muir",
            "body": "Looks good! i think this is good since it incorporates the index-time boost also at the moment.\n",
            "date": "2011-08-20T17:19:17.910+0000",
            "id": 1
        },
        {
            "author": "Robert Muir",
            "body": "I committed this, tests pass, thanks David!",
            "date": "2011-08-20T17:22:19.443+0000",
            "id": 2
        }
    ],
    "component": "core/query/scoring, general/javadocs, modules/examples",
    "description": null,
    "hasPatch": true,
    "hasScreenshot": false,
    "id": "LUCENE-3385",
    "issuetypeClassified": "IMPROVEMENT",
    "issuetypeTracker": "",
    "priority": "Major",
    "product": "LUCENE",
    "project": "LUCENE",
    "summary": "EasySimilarity to interpret document length as float",
    "systemSpecification": true,
    "version": ""
}