{
    "comments": [],
    "component": "",
    "description": "PerFieldCodecWrapper lets you set the Codec for each field; I'll promote to core & mark experimental.",
    "hasPatch": false,
    "hasScreenshot": false,
    "id": "LUCENE-2489",
    "issuetypeClassified": "REFACTORING",
    "issuetypeTracker": "IMPROVEMENT",
    "priority": "Major",
    "product": "LUCENE",
    "project": "LUCENE",
    "summary": "promote TestExternalCodecs.PerFieldCodecWrapper to core",
    "systemSpecification": true,
    "version": ""
}