{
    "comments": [
        {
            "author": "Jukka Zitting",
            "body": "The JCA package now supports a RepositoryURI parameter that can be used to connect to any JCR repository that supports the JcrUtils.getRepository() conventions.",
            "date": "2010-03-16T16:53:47.027+0000",
            "id": 0
        }
    ],
    "component": "jackrabbit-jca",
    "description": "The jackrabbit-jca package currently has hardcoded references to jackrabbit-core, which makes it difficult to reuse the packaging and related code with other JCR implementations. With the RepositoryFactory interface from JCR 2.0 we can avoid this hard dependency.",
    "hasPatch": false,
    "hasScreenshot": false,
    "id": "JCR-2555",
    "issuetypeClassified": "REFACTORING",
    "issuetypeTracker": "IMPROVEMENT",
    "priority": "Major",
    "product": "JACKRABBIT",
    "project": "JACKRABBIT",
    "summary": "Improved reusability of the JCA package",
    "systemSpecification": true,
    "version": ""
}