{
    "comments": [
        {
            "author": "Michael D\u00fcrig",
            "body": "Fixed in revision: 820674",
            "date": "2009-10-01T14:51:19.161+0000",
            "id": 0
        }
    ],
    "component": "jackrabbit-jcr-tests",
    "description": "org.apache.jackrabbit.test.api.NodeRemoveMixinTest.testCheckedIn() and \norg.apache.jackrabbit.test.api.NodeAddMixinTest.testCheckedIn() \n\nfail when the mixin being added is already present on the node. The tests should check for this and trow a NotExecutableException.",
    "hasPatch": false,
    "hasScreenshot": false,
    "id": "JCR-2338",
    "issuetypeClassified": "OTHER",
    "issuetypeTracker": "BUG",
    "priority": "Major",
    "product": "JACKRABBIT",
    "project": "JACKRABBIT",
    "summary": "Tests not executable for already present mixins",
    "systemSpecification": true,
    "version": "2.0"
}