{
    "comments": [
        {
            "author": "Marcel Reutegger",
            "body": "Fixed in revision: 831900",
            "date": "2009-11-02T14:15:20.404+0000",
            "id": 0
        }
    ],
    "component": "jackrabbit-core",
    "description": "XPath queries of the kind \"/jcr:root[<any property constraint>]\" apparently always match.",
    "hasPatch": false,
    "hasScreenshot": false,
    "id": "JCR-1987",
    "issuetypeClassified": "BUG",
    "issuetypeTracker": "BUG",
    "priority": "Minor",
    "product": "JACKRABBIT",
    "project": "JACKRABBIT",
    "summary": "Jackrabbit's lucene based query implementation does not check property constraints on the root node.",
    "systemSpecification": true,
    "version": ""
}