{
    "comments": [
        {
            "author": "Jukka Zitting",
            "body": "Simple lifecycle mechanism implemented in jackrabbit-core, and TCK tests added in jackrabbit-jcr-tests. Resolving as Fixed.",
            "date": "2009-07-17T16:37:54.747+0000",
            "id": 0
        }
    ],
    "component": "jackrabbit-core, jackrabbit-jcr-tests, jackrabbit-jcr2spi, jackrabbit-spi, jackrabbit-spi2jcr",
    "description": "JSR 283 specifies a simple lifecycle management mechanism for nodes, and as the reference implementation we should implement that feature. We also need to implement the related TCK tests.\n\nThis feature introduces a few new API methods, but during Jackrabbit 1.x we can just introduce them as custom jsr-283 API extensions.\n",
    "hasPatch": false,
    "hasScreenshot": false,
    "id": "JCR-1565",
    "issuetypeClassified": "RFE",
    "issuetypeTracker": "",
    "priority": "Major",
    "product": "JACKRABBIT",
    "project": "JACKRABBIT",
    "summary": "JSR 283 lifecycle management",
    "systemSpecification": true,
    "version": ""
}