{
    "comments": [
        {
            "author": "Tobias Bocanegra",
            "body": "improved versioning startup by removing intermediate virtual layer.\n\nfixed in r191172",
            "date": "2005-06-18T01:20:06.000+0000",
            "id": 0
        },
        {
            "author": "Stefan Guggisberg",
            "body": "closing resolved issue",
            "date": "2005-11-11T01:45:47.000+0000",
            "id": 1
        }
    ],
    "component": "",
    "description": "jackrabbit startup gets slower the more items are in the repository.\n\npossible reasons:\n- versioning\n- search index",
    "hasPatch": false,
    "hasScreenshot": false,
    "id": "JCR-127",
    "issuetypeClassified": "IMPROVEMENT",
    "issuetypeTracker": "RFE",
    "priority": "Major",
    "product": "JACKRABBIT",
    "project": "JACKRABBIT",
    "summary": "Speedup Startup",
    "systemSpecification": true,
    "version": ""
}