{
    "comments": [
        {
            "author": "Marcel Reutegger",
            "body": "- Changed EventImpl to return the path of the child item associated with the event\n- Changed SearchManager handling for property change events related to wrong path returned by Event.getPath()\n\nFixed in SVN revision 56655",
            "date": "2004-11-05T09:19:24.000+0000",
            "id": 0
        }
    ],
    "component": "",
    "description": "Path returned by Event.getPath() is wrong. It always returns the path to the parent node connected to the event. That is, if e.g. a node /foo/bar is created the path /foo is returned instead of /foo/bar.\n\nThis issue had been introduced with changed from api version 0.14 to 0.15.",
    "hasPatch": false,
    "hasScreenshot": false,
    "id": "JCR-16",
    "issuetypeClassified": "BUG",
    "issuetypeTracker": "BUG",
    "priority": "Major",
    "product": "JACKRABBIT",
    "project": "JACKRABBIT",
    "summary": "Observation tests fail",
    "systemSpecification": true,
    "version": ""
}