{
    "comments": [
        {
            "author": "Jukka Zitting",
            "body": "Done in revisions 1157043, 1157044, 1157062 and 1157063.",
            "date": "2011-08-12T12:17:46.151+0000",
            "id": 0
        }
    ],
    "component": "maven",
    "description": "We're quite a bit behind the latest and greatest of the Apache parent POMs (org.apache:apache), mostly since we're inheriting it through the now mostly unused org.apache.jackrabbit:parent POM.\n\nI'd like to move things back from the o.a.j:parent POM to the jackrabbit-parent POM that's located inside trunk. This will allow us to upgrade to the latest Apache parent POM without the trouble of an extra release of the o.a.j:parent POM.",
    "hasPatch": false,
    "hasScreenshot": false,
    "id": "JCR-3048",
    "issuetypeClassified": "OTHER",
    "issuetypeTracker": "IMPROVEMENT",
    "priority": "Minor",
    "product": "JACKRABBIT",
    "project": "JACKRABBIT",
    "summary": "Upgrade to latest Apache parent POM",
    "systemSpecification": true,
    "version": ""
}