{
    "comments": [
        {
            "author": "Martijn Hendriks",
            "body": "Added the zip file with the project source code.",
            "date": "2007-04-27T11:55:32.365+0000",
            "id": 0
        },
        {
            "author": "Stefan Guggisberg",
            "body": "nice! thanks for the contribution!\n\ncheers\nstefan",
            "date": "2007-04-27T12:38:34.117+0000",
            "id": 1
        },
        {
            "author": "Jukka Zitting",
            "body": "Committed the contributed sources to contrib/jackrabbit-jcr-import-export-tool in revision 540416. Thanks!\n\nI'd like to see the tool included in Jackrabbit 1.4, so I'll probably follow up later on with a separate issue to upgrade the tool from contrib.",
            "date": "2007-05-22T10:16:21.991+0000",
            "id": 2
        }
    ],
    "component": "",
    "description": "We at <GX> creative online development would like to contribute our command-line import-export tool to the Apache Jackrabbit project. This tool is capable of exporting and importing all kinds of repository content (including custom nodetypes and namespace mappings) in a persistence-layer independent way. ",
    "hasPatch": false,
    "hasScreenshot": false,
    "id": "JCR-891",
    "issuetypeClassified": "RFE",
    "issuetypeTracker": "RFE",
    "priority": "Minor",
    "product": "JACKRABBIT",
    "project": "JACKRABBIT",
    "summary": "Add import-export tool",
    "systemSpecification": true,
    "version": ""
}